wbx/__init__.py
wbx/client.py
wbx/utils.py
wbx-0.1.0.dist-info/METADATA
wbx-0.1.0.dist-info/WHEEL
wbx-0.1.0.dist-info/top_level.txt
wbx-0.1.0.dist-info/RECORD
