Metadata-Version: 2.4
Name: wbx
Version: 0.1.0
Summary: W&B SDK extension to fetch runs for further analysis.
Requires-Python: >=3.9
Requires-Dist: pandas>=2.3.2
Requires-Dist: pip>=25.2
Requires-Dist: pyarrow>=21.0.0
Requires-Dist: rich>=14.1.0
Requires-Dist: textual>=6.1.0
Requires-Dist: tqdm>=4.67.1
Requires-Dist: typer>=0.17.4
Requires-Dist: wandb>=0.21.3
